{
  "metadata": {
    "dataset": "Chinatown",
    "batch_size": 8,
    "epochs": 200,
    "total_scenarios": 11,
    "successful_scenarios": 11,
    "timestamp": "20250828_143816"
  },
  "results": [
    {
      "scenario": "Baseline",
      "description": "Standard TS2vec without any enhancements",
      "dataset": "Chinatown",
      "accuracy": 0.9825072886297376,
      "runtime_seconds": 8.265799045562744,
      "batch_size": 8,
      "epochs": 200,
      "status": "success",
      "amc_instance": 0.0,
      "amc_temporal": 0.0,
      "amc_margin": 0.5,
      "min_tau": 0.4,
      "max_tau": 0.4,
      "temp_method": "fixed",
      "timestamp": "2025-08-28T18:36:17.766365"
    },
    {
      "scenario": "AMC_Instance",
      "description": "Angular Margin Contrastive for instance discrimination",
      "dataset": "Chinatown",
      "accuracy": 0.9795918367346939,
      "runtime_seconds": 10.076401233673096,
      "batch_size": 8,
      "epochs": 200,
      "status": "success",
      "amc_instance": 1.0,
      "amc_temporal": 0.0,
      "amc_margin": 0.5,
      "min_tau": 0.4,
      "max_tau": 0.4,
      "temp_method": "fixed",
      "timestamp": "2025-08-28T18:36:27.842934"
    },
    {
      "scenario": "AMC_Temporal",
      "description": "Angular Margin Contrastive for temporal relationships",
      "dataset": "Chinatown",
      "accuracy": 0.9825072886297376,
      "runtime_seconds": 10.837833642959595,
      "batch_size": 8,
      "epochs": 200,
      "status": "success",
      "amc_instance": 0.0,
      "amc_temporal": 1.0,
      "amc_margin": 0.5,
      "min_tau": 0.4,
      "max_tau": 0.4,
      "temp_method": "fixed",
      "timestamp": "2025-08-28T18:36:38.680945"
    },
    {
      "scenario": "Temperature_Scheduling",
      "description": "Cosine annealing temperature scheduling (0.15-0.75)",
      "dataset": "Chinatown",
      "accuracy": 0.9825072886297376,
      "runtime_seconds": 8.384576797485352,
      "batch_size": 8,
      "epochs": 200,
      "status": "success",
      "amc_instance": 0.0,
      "amc_temporal": 0.0,
      "amc_margin": 0.5,
      "min_tau": 0.15,
      "max_tau": 0.75,
      "temp_method": "cosine_annealing",
      "timestamp": "2025-08-28T18:36:47.065714"
    },
    {
      "scenario": "AMC_Both",
      "description": "Combined AMC instance and temporal losses",
      "dataset": "Chinatown",
      "accuracy": 0.9854227405247813,
      "runtime_seconds": 12.367156028747559,
      "batch_size": 8,
      "epochs": 200,
      "status": "success",
      "amc_instance": 0.7,
      "amc_temporal": 0.5,
      "amc_margin": 0.5,
      "min_tau": 0.4,
      "max_tau": 0.4,
      "temp_method": "fixed",
      "timestamp": "2025-08-28T18:36:59.433045"
    },
    {
      "scenario": "AMC_Temperature_Scheduling",
      "description": "AMC losses with temperature scheduling (0.15-0.75)",
      "dataset": "Chinatown",
      "accuracy": 0.9854227405247813,
      "runtime_seconds": 12.321225881576538,
      "batch_size": 8,
      "epochs": 200,
      "status": "success",
      "amc_instance": 1.0,
      "amc_temporal": 0.5,
      "amc_margin": 0.5,
      "min_tau": 0.15,
      "max_tau": 0.75,
      "temp_method": "cosine_annealing",
      "timestamp": "2025-08-28T18:37:11.754465"
    },
    {
      "scenario": "High_AMC_Instance",
      "description": "High AMC instance coefficient (2.0)",
      "dataset": "Chinatown",
      "accuracy": 0.9854227405247813,
      "runtime_seconds": 12.538505554199219,
      "batch_size": 8,
      "epochs": 200,
      "status": "success",
      "amc_instance": 2.0,
      "amc_temporal": 0.5,
      "amc_margin": 0.4,
      "min_tau": 0.15,
      "max_tau": 0.75,
      "temp_method": "cosine_annealing",
      "timestamp": "2025-08-28T18:37:24.293186"
    },
    {
      "scenario": "High_AMC_Temporal",
      "description": "High AMC temporal coefficient (2.0)",
      "dataset": "Chinatown",
      "accuracy": 0.9883381924198251,
      "runtime_seconds": 12.723897695541382,
      "batch_size": 8,
      "epochs": 200,
      "status": "success",
      "amc_instance": 1.0,
      "amc_temporal": 2.0,
      "amc_margin": 0.4,
      "min_tau": 0.15,
      "max_tau": 0.75,
      "temp_method": "cosine_annealing",
      "timestamp": "2025-08-28T18:37:37.017289"
    },
    {
      "scenario": "Tight_Temperature",
      "description": "Tight temperature range (0.1-0.5) with AMC",
      "dataset": "Chinatown",
      "accuracy": 0.9795918367346939,
      "runtime_seconds": 12.446851253509521,
      "batch_size": 8,
      "epochs": 200,
      "status": "success",
      "amc_instance": 1.0,
      "amc_temporal": 0.5,
      "amc_margin": 0.5,
      "min_tau": 0.1,
      "max_tau": 0.5,
      "temp_method": "cosine_annealing",
      "timestamp": "2025-08-28T18:37:49.464331"
    },
    {
      "scenario": "Wide_Temperature",
      "description": "Wide temperature range (0.05-0.9) with AMC",
      "dataset": "Chinatown",
      "accuracy": 0.9737609329446064,
      "runtime_seconds": 12.582430362701416,
      "batch_size": 8,
      "epochs": 200,
      "status": "success",
      "amc_instance": 1.0,
      "amc_temporal": 0.5,
      "amc_margin": 0.5,
      "min_tau": 0.05,
      "max_tau": 0.9,
      "temp_method": "cosine_annealing",
      "timestamp": "2025-08-28T18:38:02.046934"
    },
    {
      "scenario": "Optimized_Efficient",
      "description": "High-performance configuration (AMC 10.0/7.53, temp 0.05-0.76)",
      "dataset": "Chinatown",
      "accuracy": 0.0,
      "runtime_seconds": 14.29819107055664,
      "efficiency_mode": true,
      "time_reduction_percent": 0.0,
      "memory_reduction_percent": 0.0,
      "optimizations_applied": [],
      "status": "success",
      "amc_instance": 10.0,
      "amc_temporal": 7.53,
      "amc_margin": 0.3,
      "min_tau": 0.05,
      "max_tau": 0.76,
      "t_max": 25.0,
      "temp_method": "cosine_annealing",
      "optimization_type": "computational_efficiency",
      "timestamp": "2025-08-28T18:38:16.345258"
    }
  ]
}